db_query_profiler/__init__.py
db_query_profiler/query_timer.py
db_query_profiler-0.0.8.dist-info/licenses/LICENSE
db_query_profiler-0.0.8.dist-info/METADATA
db_query_profiler-0.0.8.dist-info/WHEEL
db_query_profiler-0.0.8.dist-info/top_level.txt
db_query_profiler-0.0.8.dist-info/RECORD
