Metadata-Version: 2.4
Name: db_query_profiler
Version: 0.0.8
Summary: Lightweight database query profiler.
Author: billwallis
Requires-Python: >=3.9
License-File: LICENSE
Requires-Dist: tqdm>=4.0.0
Dynamic: license-file
